bitfinex/__init__.py
bitfinex/backtest/__init__.py
bitfinex/backtest/data.py
bitfinex/rest/__init__.py
bitfinex/rest/restv1.py
bitfinex/rest/restv2.py
bitfinex/utils/__init__.py
bitfinex/websockets/__init__.py
bitfinex/websockets/abbreviations.py
bitfinex/websockets/client.py
tests/__init__.py
tests/test_rest_v1.py
tests/test_rest_v2.py
tests/test_utils.py
bitfinex_v2-1.8.0.dist-info/LICENSE.md
bitfinex_v2-1.8.0.dist-info/METADATA
bitfinex_v2-1.8.0.dist-info/WHEEL
bitfinex_v2-1.8.0.dist-info/top_level.txt
bitfinex_v2-1.8.0.dist-info/zip-safe
bitfinex_v2-1.8.0.dist-info/RECORD
