Metadata-Version: 2.1
Name: bitfinex-v2
Version: 1.8.0
Summary: Python client for the Bitfinex API
Home-page: https://github.com/ohenrik/bitfinex
Author: Ole Henrik Skogstrøm
Author-email: henrik@amplify.no
License: MIT
Keywords: bitcoin,btc
Platform: UNKNOWN
Requires-Dist: requests
Requires-Dist: httpretty
Requires-Dist: twisted
Requires-Dist: autobahn
Requires-Dist: pyopenssl
Requires-Dist: service-identity
